tests/__init__.py
tests/test_vigil.py
vigil_reporter/__init__.py
vigil_reporter/reporter.py
py_vigil_reporter-0.2.0.dist-info/LICENSE
py_vigil_reporter-0.2.0.dist-info/METADATA
py_vigil_reporter-0.2.0.dist-info/WHEEL
py_vigil_reporter-0.2.0.dist-info/top_level.txt
py_vigil_reporter-0.2.0.dist-info/RECORD
