Metadata-Version: 2.1
Name: py-vigil-reporter
Version: 0.2.0
Summary: Vigil Reporter for Python
Home-page: https://github.com/M0r13n/py-vigil-reporter
Author: Leon Morten Richter
Author-email: leon.morten@gmail.com
License: MIT
Platform: UNKNOWN
Classifier: License :: OSI Approved :: MIT License
Classifier: Programming Language :: Python :: 3
Classifier: Programming Language :: Python :: 3.7
Requires-Python: >=3.6
Requires-Dist: requests
Requires-Dist: psutil (>=5.7.0)
